streaminghub_datamux/__init__.py
streaminghub_datamux/__main__.py
streaminghub_datamux/api.py
streaminghub_datamux/rpc.py
streaminghub_datamux/transforms.py
streaminghub_datamux/typing.py
streaminghub_datamux/util.py
streaminghub_datamux/cli/__init__.py
streaminghub_datamux/cli/relay.py
streaminghub_datamux/cli/replay.py
streaminghub_datamux/cli/simulate.py
streaminghub_datamux/managers/__init__.py
streaminghub_datamux/managers/collection_manager.py
streaminghub_datamux/managers/proxy_manager.py
streaminghub_datamux/managers/simulation_manager.py
streaminghub_datamux/managers/util.py
streaminghub_datamux/remote/__init__.py
streaminghub_datamux/remote/api.py
streaminghub_datamux/remote/server.py
streaminghub_datamux/remote/topics.py
streaminghub_datamux-0.1.8.dist-info/LICENSE
streaminghub_datamux-0.1.8.dist-info/METADATA
streaminghub_datamux-0.1.8.dist-info/WHEEL
streaminghub_datamux-0.1.8.dist-info/top_level.txt
streaminghub_datamux-0.1.8.dist-info/RECORD
