Metadata-Version: 2.1
Name: streaminghub-datamux
Version: 0.1.8
Summary: A library to stream data into real-time analytics pipelines
Author-email: Yasith Jayawardana <yasith@cs.odu.edu>
License: Copyright (c) 2024 Old Dominion University
Project-URL: homepage, https://github.com/nirdslab/streaminghub/tree/master/datamux
Keywords: dfds,metadata,parser
Classifier: Programming Language :: Python :: 3
Classifier: License :: OSI Approved :: MIT License
Classifier: Operating System :: OS Independent
Requires-Python: >=3.10
License-File: LICENSE
Requires-Dist: streaminghub-pydfds
Requires-Dist: multiprocess
Requires-Dist: numpy
Requires-Dist: pandas
Requires-Dist: pyarrow
Requires-Dist: rich
Provides-Extra: dev
Requires-Dist: build ; extra == 'dev'
Requires-Dist: twine ; extra == 'dev'
Requires-Dist: bumpver ; extra == 'dev'
Requires-Dist: pip-tools ; extra == 'dev'
Requires-Dist: pytest ; extra == 'dev'
Requires-Dist: tqdm ; extra == 'dev'
